feishu_bot/__init__.py
feishu_bot/bot.py
feishu_bot/errors.py
feishu_bot/log.py
tests/__init__.py
tests/test_bot.py
feishu_bot-0.0.5.dist-info/LICENSE
feishu_bot-0.0.5.dist-info/METADATA
feishu_bot-0.0.5.dist-info/WHEEL
feishu_bot-0.0.5.dist-info/top_level.txt
feishu_bot-0.0.5.dist-info/RECORD
